fds/__init__.py
fds/sdk/__init__.py
fds/sdk/AITextSummarization/__init__.py
fds/sdk/AITextSummarization/api_client.py
fds/sdk/AITextSummarization/configuration.py
fds/sdk/AITextSummarization/exceptions.py
fds/sdk/AITextSummarization/model_utils.py
fds/sdk/AITextSummarization/rest.py
fds/sdk/AITextSummarization/api/__init__.py
fds/sdk/AITextSummarization/api/default_api.py
fds/sdk/AITextSummarization/apis/__init__.py
fds/sdk/AITextSummarization/model/__init__.py
fds/sdk/AITextSummarization/model/bad_request_response.py
fds/sdk/AITextSummarization/model/internal_server_error_response.py
fds/sdk/AITextSummarization/model/request.py
fds/sdk/AITextSummarization/model/success_response.py
fds/sdk/AITextSummarization/models/__init__.py
fds.sdk.AITextSummarization-0.21.14.dist-info/LICENSE
fds.sdk.AITextSummarization-0.21.14.dist-info/METADATA
fds.sdk.AITextSummarization-0.21.14.dist-info/WHEEL
fds.sdk.AITextSummarization-0.21.14.dist-info/top_level.txt
fds.sdk.AITextSummarization-0.21.14.dist-info/RECORD
